deepcompress/__init__.py
deepcompress/cli.py
deepcompress/exceptions.py
deepcompress/worker.py
deepcompress/core/__init__.py
deepcompress/core/compressor.py
deepcompress/core/config.py
deepcompress/core/extractor.py
deepcompress/core/optimizer.py
deepcompress/integrations/__init__.py
deepcompress/integrations/cache.py
deepcompress/integrations/llm.py
deepcompress/integrations/vector_db.py
deepcompress/models/__init__.py
deepcompress/models/document.py
deepcompress/models/response.py
deepcompress/processing/__init__.py
deepcompress/processing/batch.py
deepcompress/processing/pii.py
deepcompress/utils/__init__.py
deepcompress/utils/cost.py
deepcompress/utils/logging.py
deepcompress/utils/metrics.py
deepcompress-1.4.5.dist-info/licenses/LICENSE
deepcompress-1.4.5.dist-info/METADATA
deepcompress-1.4.5.dist-info/WHEEL
deepcompress-1.4.5.dist-info/entry_points.txt
deepcompress-1.4.5.dist-info/top_level.txt
deepcompress-1.4.5.dist-info/RECORD
