Metadata-Version: 2.4
Name: deepcompress
Version: 1.4.5
Summary: Production-ready document compression library reducing LLM costs by 96% with DeepSeek-OCR integration
Author-email: Your Organization <engineering@yourorg.com>
License-Expression: MIT
Project-URL: Homepage, https://github.com/your-org/deepcompress
Project-URL: Documentation, https://deepcompress.readthedocs.io
Project-URL: Repository, https://github.com/your-org/deepcompress
Project-URL: Changelog, https://github.com/your-org/deepcompress/blob/main/CHANGELOG.md
Keywords: document-processing,ocr,llm,compression,rag,deepseek,financial-services
Classifier: Development Status :: 5 - Production/Stable
Classifier: Intended Audience :: Developers
Classifier: Intended Audience :: Financial and Insurance Industry
Classifier: Programming Language :: Python :: 3.9
Classifier: Programming Language :: Python :: 3.10
Classifier: Programming Language :: Python :: 3.11
Classifier: Programming Language :: Python :: 3.12
Classifier: Topic :: Scientific/Engineering :: Artificial Intelligence
Classifier: Topic :: Text Processing :: General
Requires-Python: >=3.9
License-File: LICENSE
Requires-Dist: pydantic<3.0.0,>=2.5.0
Requires-Dist: pydantic-settings<3.0.0,>=2.1.0
Requires-Dist: aiofiles<24.0.0,>=23.2.0
Requires-Dist: httpx<1.0.0,>=0.25.0
Requires-Dist: redis<6.0.0,>=5.0.0
Requires-Dist: prometheus-client<1.0.0,>=0.19.0
Requires-Dist: python-dotenv<2.0.0,>=1.0.0
Requires-Dist: tenacity<9.0.0,>=8.2.0
Requires-Dist: cryptography<44.0.0,>=41.0.0
Requires-Dist: orjson<4.0.0,>=3.9.0
Provides-Extra: gpu
Requires-Dist: torch<3.0.0,>=2.0.0; extra == "gpu"
Requires-Dist: transformers<5.0.0,>=4.38.0; extra == "gpu"
Requires-Dist: tokenizers<1.0.0,>=0.19.0; extra == "gpu"
Requires-Dist: pillow>=10.0.0; extra == "gpu"
Requires-Dist: pdf2image>=1.17.0; extra == "gpu"
Requires-Dist: accelerate>=0.20.0; extra == "gpu"
Requires-Dist: sentencepiece>=0.1.99; extra == "gpu"
Requires-Dist: addict>=2.4.0; extra == "gpu"
Requires-Dist: tqdm>=4.65.0; extra == "gpu"
Provides-Extra: colab
Requires-Dist: tokenizers<1.0.0,>=0.19.0; extra == "colab"
Requires-Dist: pillow>=10.0.0; extra == "colab"
Requires-Dist: pdf2image>=1.17.0; extra == "colab"
Requires-Dist: accelerate>=0.20.0; extra == "colab"
Requires-Dist: sentencepiece>=0.1.99; extra == "colab"
Requires-Dist: addict>=2.4.0; extra == "colab"
Requires-Dist: tqdm>=4.65.0; extra == "colab"
Provides-Extra: gpu-flash
Requires-Dist: deepcompress[gpu]; extra == "gpu-flash"
Requires-Dist: flash-attn<2.8.0,>=2.3.0; platform_machine == "x86_64" and extra == "gpu-flash"
Provides-Extra: aws
Requires-Dist: boto3<2.0.0,>=1.34.0; extra == "aws"
Requires-Dist: aioboto3<13.0.0,>=12.3.0; extra == "aws"
Provides-Extra: vector-db
Requires-Dist: pinecone-client<4.0.0,>=3.0.0; extra == "vector-db"
Requires-Dist: weaviate-client<5.0.0,>=4.4.0; extra == "vector-db"
Provides-Extra: llm
Requires-Dist: openai<2.0.0,>=1.6.0; extra == "llm"
Requires-Dist: anthropic<1.0.0,>=0.8.0; extra == "llm"
Provides-Extra: dev
Requires-Dist: pytest>=7.4.0; extra == "dev"
Requires-Dist: pytest-asyncio>=0.21.0; extra == "dev"
Requires-Dist: pytest-cov>=4.1.0; extra == "dev"
Requires-Dist: pytest-mock>=3.12.0; extra == "dev"
Requires-Dist: black>=23.12.0; extra == "dev"
Requires-Dist: ruff>=0.1.8; extra == "dev"
Requires-Dist: mypy>=1.7.0; extra == "dev"
Requires-Dist: pre-commit>=3.6.0; extra == "dev"
Provides-Extra: all
Requires-Dist: deepcompress[aws,dev,gpu,llm,vector-db]; extra == "all"
Provides-Extra: all-flash
Requires-Dist: deepcompress[aws,dev,gpu-flash,llm,vector-db]; extra == "all-flash"
Dynamic: license-file
